rtat/__init__.py
rtat/anon.py
rtat/contours.py
rtat/dvhs.py
rtat/info.py
rtat/tools.py
rtat-0.1.4.dist-info/licenses/LICENSE.txt
rtat-0.1.4.dist-info/METADATA
rtat-0.1.4.dist-info/WHEEL
rtat-0.1.4.dist-info/top_level.txt
rtat-0.1.4.dist-info/RECORD
