Metadata-Version: 2.4
Name: rtat
Version: 0.1.4
Summary: A package to Analysis Proton Therapy Data
Home-page: https://github.com/pabloyepes/rtat
Author: Pablo Yepes
Author-email: yepes@rice.edu
Classifier: Programming Language :: Python :: 3
Classifier: License :: OSI Approved :: MIT License
Classifier: Operating System :: OS Independent
Requires-Python: >=3.6
License-File: LICENSE.txt
Dynamic: author
Dynamic: author-email
Dynamic: classifier
Dynamic: description
Dynamic: description-content-type
Dynamic: home-page
Dynamic: license-file
Dynamic: requires-python
Dynamic: summary
